jules/__init__.py
rafa/Engine.py
rafa/Rafa.py
rafa/__init__.py
rafa/main.py
rafa-0.0.10.dist-info/DESCRIPTION.rst
rafa-0.0.10.dist-info/METADATA
rafa-0.0.10.dist-info/RECORD
rafa-0.0.10.dist-info/WHEEL
rafa-0.0.10.dist-info/entry_points.txt
rafa-0.0.10.dist-info/metadata.json
rafa-0.0.10.dist-info/top_level.txt
