Metadata-Version: 2.0
Name: rafa
Version: 0.0.10
Summary: A data transformation tool for analytics teams
Home-page: UNKNOWN
Author: Michael Irvine
Author-email: michael.j.irvine@gmail.com
License: UNKNOWN
Keywords: python,first package
Platform: UNKNOWN
Classifier: Development Status :: 1 - Planning
Classifier: Intended Audience :: Developers
Classifier: Programming Language :: Python :: 3
Classifier: Operating System :: MacOS :: MacOS X
Classifier: Operating System :: Microsoft :: Windows
Classifier: Operating System :: POSIX :: Linux
License-File: LICENSE
Requires-Dist: rafa-db
Requires-Dist: python-dotenv
Requires-Dist: psycopg2-binary
Requires-Dist: google-cloud-bigquery
